asmu/__init__.py
asmu/acore.py
asmu/afile.py
asmu/analyzer.py
asmu/asetup.py
asmu/effect.py
asmu/exceptions.py
asmu/generator.py
asmu/interface.py
asmu/io.py
asmu/processor.py
asmu/typing.py
asmu-0.1.9.dist-info/METADATA
asmu-0.1.9.dist-info/WHEEL
asmu-0.1.9.dist-info/licenses/LICENSE
asmu-0.1.9.dist-info/RECORD
